pykrev/__init__.py
pykrev/diversity/__init__.py
pykrev/diversity/bray_curtis_matrix.py
pykrev/diversity/compound_class.py
pykrev/diversity/diversity_indices.py
pykrev/diversity/normalise_intensity.py
pykrev/diversity/ordination_matrix.py
pykrev/diversity/page_rank.py
pykrev/diversity/compound_data/Brite_All_DF.csv
pykrev/diversity/compound_data/Brite_BioMol_DF.csv
pykrev/diversity/compound_data/Brite_Lipid_DF.csv
pykrev/diversity/compound_data/Brite_Pesticide_DF.csv
pykrev/diversity/compound_data/Brite_Phyto_DF.csv
pykrev/diversity/compound_data/Brite_Toxin_DF.csv
pykrev/formula/__init__.py
pykrev/formula/aromaticity_index.py
pykrev/formula/average_mstuple.py
pykrev/formula/calculate_mass.py
pykrev/formula/double_bond_equivalent.py
pykrev/formula/element_counts.py
pykrev/formula/element_ratios.py
pykrev/formula/filter_spectral_interference.py
pykrev/formula/find_intersections.py
pykrev/formula/kendrick_mass_defect.py
pykrev/formula/msTuple.py
pykrev/formula/msTupleDict.py
pykrev/formula/nominal_oxidation_state.py
pykrev/formula/read_batch_formularity.py
pykrev/formula/read_corems.py
pykrev/formula/read_csv.py
pykrev/formula/read_formularity.py
pykrev/plotting/__init__.py
pykrev/plotting/atomic_class_plot.py
pykrev/plotting/compound_class_plot.py
pykrev/plotting/kendrick_mass_defect_plot.py
pykrev/plotting/mass_histogram.py
pykrev/plotting/mass_spectrum.py
pykrev/plotting/multi_van_krevelen_plot.py
pykrev/plotting/reaction_network.py
pykrev/plotting/spiral_plot.py
pykrev/plotting/van_krevelen_histogram.py
pykrev/plotting/van_krevelen_plot.py
pykrev-1.2.4.dist-info/LICENSE
pykrev-1.2.4.dist-info/METADATA
pykrev-1.2.4.dist-info/WHEEL
pykrev-1.2.4.dist-info/top_level.txt
pykrev-1.2.4.dist-info/RECORD
