Metadata-Version: 2.1
Name: pykrev
Version: 1.2.4
Summary: FT-MS data analysis in Python
Home-page: https://github.com/kzra/pykrev
Author: Ezra Kitson
Author-email: ezrakitson@ed.ac.uk
License: UNKNOWN
Platform: UNKNOWN
Classifier: Programming Language :: Python :: 3
Classifier: License :: OSI Approved :: MIT License
Classifier: Operating System :: OS Independent
Requires-Python: >=3.6
